dodopayments/__init__.py
dodopayments/_base_client.py
dodopayments/_client.py
dodopayments/_compat.py
dodopayments/_constants.py
dodopayments/_exceptions.py
dodopayments/_files.py
dodopayments/_models.py
dodopayments/_qs.py
dodopayments/_resource.py
dodopayments/_response.py
dodopayments/_streaming.py
dodopayments/_types.py
dodopayments/_version.py
dodopayments/pagination.py
dodopayments/py.typed
dodopayments/_utils/__init__.py
dodopayments/_utils/_compat.py
dodopayments/_utils/_datetime_parse.py
dodopayments/_utils/_logs.py
dodopayments/_utils/_proxy.py
dodopayments/_utils/_reflection.py
dodopayments/_utils/_resources_proxy.py
dodopayments/_utils/_streams.py
dodopayments/_utils/_sync.py
dodopayments/_utils/_transform.py
dodopayments/_utils/_typing.py
dodopayments/_utils/_utils.py
dodopayments/lib/.keep
dodopayments/resources/__init__.py
dodopayments/resources/addons.py
dodopayments/resources/brands.py
dodopayments/resources/checkout_sessions.py
dodopayments/resources/discounts.py
dodopayments/resources/disputes.py
dodopayments/resources/license_key_instances.py
dodopayments/resources/license_keys.py
dodopayments/resources/licenses.py
dodopayments/resources/meters.py
dodopayments/resources/misc.py
dodopayments/resources/payments.py
dodopayments/resources/payouts.py
dodopayments/resources/refunds.py
dodopayments/resources/subscriptions.py
dodopayments/resources/usage_events.py
dodopayments/resources/customers/__init__.py
dodopayments/resources/customers/customer_portal.py
dodopayments/resources/customers/customers.py
dodopayments/resources/customers/wallets/__init__.py
dodopayments/resources/customers/wallets/ledger_entries.py
dodopayments/resources/customers/wallets/wallets.py
dodopayments/resources/invoices/__init__.py
dodopayments/resources/invoices/invoices.py
dodopayments/resources/invoices/payments.py
dodopayments/resources/products/__init__.py
dodopayments/resources/products/images.py
dodopayments/resources/products/products.py
dodopayments-1.75.1.dist-info/METADATA
dodopayments-1.75.1.dist-info/WHEEL
dodopayments-1.75.1.dist-info/licenses/LICENSE
dodopayments-1.75.1.dist-info/RECORD
